emirpred/MERCI/MERCI_motif_locator.pl
emirpred/MERCI/merci_ids.txt
emirpred/MERCI/pos_test.txt
emirpred/MERCI/pos_test_g1.txt
emirpred/MERCI/train_pos_motifs.txt
emirpred/MERCI/train_pos_motifs_g1.txt
emirpred/Standalone_Nfeature/RNA_Standalone/Nfeature_RNA.py
emirpred/Standalone_Nfeature/RNA_Standalone/Data/RDK.py
emirpred/Standalone_Nfeature/RNA_Standalone/Data/PaxHeader/BinaryProfile_dinucleotide.py
emirpred/Standalone_Nfeature/RNA_Standalone/Data/PaxHeader/BinaryProfile_dinucleotide_CT.py
emirpred/Standalone_Nfeature/RNA_Standalone/Data/PaxHeader/BinaryProfile_dinucleotide_NT.py
emirpred/Standalone_Nfeature/RNA_Standalone/Data/PaxHeader/BinaryProfile_dinucleotide_REST.py
emirpred/Standalone_Nfeature/RNA_Standalone/Data/PaxHeader/BinaryProfile_dinucleotide_SPLIT.py
emirpred/Standalone_Nfeature/RNA_Standalone/Data/PaxHeader/BinaryProfile_mononucleotide_CT.py
emirpred/Standalone_Nfeature/RNA_Standalone/Data/PaxHeader/BinaryProfile_mononucleotide_NT.py
emirpred/Standalone_Nfeature/RNA_Standalone/Data/PaxHeader/BinaryProfile_mononucleotide_REST.py
emirpred/Standalone_Nfeature/RNA_Standalone/Data/PaxHeader/BinaryProfile_mononucleotide_SPLIT.py
emirpred/Standalone_Nfeature/RNA_Standalone/Data/PaxHeader/BinaryProfile_monotide.py
emirpred/Standalone_Nfeature/RNA_Standalone/Data/PaxHeader/BinaryProfile_trinucleotide.py
emirpred/Standalone_Nfeature/RNA_Standalone/Data/PaxHeader/BinaryProfile_trinucleotide_CT.py
emirpred/Standalone_Nfeature/RNA_Standalone/Data/PaxHeader/BinaryProfile_trinucleotide_NT.py
emirpred/Standalone_Nfeature/RNA_Standalone/Data/PaxHeader/BinaryProfile_trinucleotide_REST.py
emirpred/Standalone_Nfeature/RNA_Standalone/Data/PaxHeader/BinaryProfile_trinucleotide_SPLIT.py
emirpred/Standalone_Nfeature/RNA_Standalone/Data/PaxHeader/CDK.py
emirpred/Standalone_Nfeature/RNA_Standalone/Data/PaxHeader/CDK_CT.py
emirpred/Standalone_Nfeature/RNA_Standalone/Data/PaxHeader/CDK_NT.py
emirpred/Standalone_Nfeature/RNA_Standalone/Data/PaxHeader/CDK_REST.py
emirpred-1.1.1.dist-info/LICENSE.txt
emirpred-1.1.1.dist-info/METADATA
emirpred-1.1.1.dist-info/WHEEL
emirpred-1.1.1.dist-info/entry_points.txt
emirpred-1.1.1.dist-info/top_level.txt
emirpred-1.1.1.dist-info/RECORD
