Metadata-Version: 2.1
Name: emirpred
Version: 1.1.1
Summary: A tool to predict exosomal miRNA
Home-page: https://github.com/raghavagps/emirpred
Requires-Python: >=3.6
License-File: LICENSE.txt
Requires-Dist: numpy
Requires-Dist: pandas
Requires-Dist: scikit-learn ==1.2.2
Requires-Dist: joblib
Requires-Dist: argparse
Provides-Extra: dev
Requires-Dist: pytest >=7.0 ; extra == 'dev'
Requires-Dist: twine >=4.0.2 ; extra == 'dev'
